sparks/__init__.py
sparks/console/__init__.py
sparks/console/cli.py
sparks/console/prompt.py
sparks/console/commands/__init__.py
sparks/console/commands/create.py
sparks/core/__init__.py
sparks/core/create.py
Sparks-0.1.0.dist-info/LICENSE
Sparks-0.1.0.dist-info/METADATA
Sparks-0.1.0.dist-info/WHEEL
Sparks-0.1.0.dist-info/entry_points.txt
Sparks-0.1.0.dist-info/top_level.txt
Sparks-0.1.0.dist-info/RECORD
