Metadata-Version: 2.1
Name: Sparks
Version: 0.1.0
Summary: A CLI tool that creates and updates project folders from templates to spark faster project bootstrapping.
Home-page: https://github.com/binaryart/sparks
Author: Jill San Luis
Author-email: jill.devs@gmail.com
License: MIT
Project-URL: Code, https://github.com/binaryart/sparks
Project-URL: Issue tracker, https://github.com/binaryart/sparks/issues
Platform: UNKNOWN
Classifier: Programming Language :: Python :: 3
Classifier: Programming Language :: Python :: 3.7
Requires-Python: >=3.7
Requires-Dist: click
Requires-Dist: jinja2
Requires-Dist: pyyaml
Provides-Extra: dev
Requires-Dist: black (==19.3b0) ; extra == 'dev'
Requires-Dist: pre-commit ; extra == 'dev'
Requires-Dist: pytest ; extra == 'dev'
Requires-Dist: pytest-cov ; extra == 'dev'
